dlive/__init__.py
dlive-1.0.0.dist-info/LICENSE
dlive-1.0.0.dist-info/WHEEL
dlive-1.0.0.dist-info/METADATA
dlive-1.0.0.dist-info/RECORD
