Metadata-Version: 2.1
Name: dlive
Version: 1.0.0
Summary: A Python wrapper for the DLive API.
Home-page: https://github.com/Aareon/PyDLive
License: UNKNOWN
Author: Aareon Sullivan
Author-email: aareon@died-in.space
